<object clone="/base/obj/thing" owner="SID">
  <Base:Thing>
    <Ur:UrObject urobject="OBJ(Mansion:rooms:UrOutside)"/>
    <Base:Bulk immobile="false" mass="1000" density="0.5"/>
    <Base:Container flexible="false" transparent-container="false" public-container="false" tight="false" capacity="125" maxweight="125000"/>
    <Base:Misc gender="neuter" volition="false" weapon="false" default_stance="none" combinable="false" discrete="false" by_weight="false" tight="false" scriptrunner="false">
      <Base:Edible value="false"/>
      <Base:Potable value="false"/>
      <Base:DrinkMessageFirst/>
      <Base:DrinkMessageThird/>
      <Base:Transparency value="false"/>
      <Base:Unsafe value="true"/>
      <Base:Safe value="false"/>
      <Base:ClothesExpected value="false"/>
      <Base:DieMessageFirst/>
      <Base:DieMessageThird/>
    </Base:Misc>
    <Base:Details>
      <Base:Detail id="default" prime="true" def="true" abstract="false" hidden="false" luminosity="0.5" targetable_in_dark="false" plural="false">
        <Base:Preposition close="false" against="false" under="false" on="false" inside="false" near="false" over="false" behind="false" before="false" beside="false"/>
        <Base:Names>
          <Base:SNames>
            <Base:SName sname="balcony"/>
          </Base:SNames>
          <Base:PNames>
            <Base:PName pname="balconies"/>
          </Base:PNames>
        </Base:Names>
        <Base:Adjectives>
          <Base:Adjective adjective="exterior"/>
          <Base:Adjective adjective="external"/>
          <Base:Adjective adjective="front"/>
          <Base:Adjective adjective="open"/>
          <Base:Adjective adjective="railed"/>
        </Base:Adjectives>
        <Base:Descriptions>
          <Base:Description type="brief">
             the exterior balcony
          </Base:Description>
          <Base:Description type="glance">
             An open balcony looking out over the drive and front lawns.
          </Base:Description>
          <Base:Description type="look">
             This is an open balcony, with a low stone railing protecting its edge. Past the railing, you have a view of the drive and lawns in the dim night, and the steps below.
          </Base:Description>
          <Base:Description type="mapurl">
             http://www.skotos.net/MansionGame/images/Balcony.jpg
          </Base:Description>
        </Base:Descriptions>
        <Base:Exit door="false" closed="false" locked="false" never_obvious="false" obvious_when_open="false" hidden_when_closed="false" separate="false" self-locking="false" deadbolt="false"/>
        <Base:Climbable/>
      </Base:Detail>
      <Base:Detail id="exit north" prime="false" def="true" abstract="false" hidden="false" luminosity="0" targetable_in_dark="false" plural="false">
        <Base:Preposition close="true" against="true" under="false" on="false" inside="false" near="true" over="false" behind="false" before="true" beside="true"/>
        <Base:Names>
          <Base:SNames>
            <Base:SName sname="door"/>
            <Base:SName sname="exit"/>
            <Base:SName sname="entrance"/>
            <Base:SName sname="opening"/>
            <Base:SName sname="handle"/>
            <Base:SName sname="knob"/>
            <Base:SName sname="doorknob"/>
            <Base:SName sname="lock"/>
            <Base:SName sname="keyhole"/>
          </Base:SNames>
          <Base:PNames>
            <Base:PName pname="doorknobs"/>
            <Base:PName pname="doors"/>
            <Base:PName pname="entrances"/>
            <Base:PName pname="exits"/>
            <Base:PName pname="handles"/>
            <Base:PName pname="keyholes"/>
            <Base:PName pname="knobs"/>
            <Base:PName pname="locks"/>
            <Base:PName pname="openings"/>
          </Base:PNames>
        </Base:Names>
        <Base:Adjectives>
          <Base:Adjective adjective="balcony"/>
          <Base:Adjective adjective="brass"/>
          <Base:Adjective adjective="door"/>
          <Base:Adjective adjective="exterior"/>
          <Base:Adjective adjective="external"/>
          <Base:Adjective adjective="front"/>
          <Base:Adjective adjective="north"/>
          <Base:Adjective adjective="northern"/>
          <Base:Adjective adjective="oak"/>
          <Base:Adjective adjective="panelled"/>
          <Base:Adjective adjective="wood"/>
          <Base:Adjective adjective="wooden"/>
        </Base:Adjectives>
        <Base:Descriptions>
          <Base:Description type="brief">
             the northern door
          </Base:Description>
          <Base:Description type="look">
             An oak door is set in the middle of the northern wall. A brass knob and lock are attached to the edge of the door.
          </Base:Description>
        </Base:Descriptions>
        <Base:Exit dest="NREF(Mansion:rooms:UpperPassageEast|exit south)" door="true" closed="true" locked="true" never_obvious="false" obvious_when_open="false" hidden_when_closed="false" separate="false" keycode="Gables" self-locking="false" deadbolt="false">
          <Base:Direction dir="north"/>
        </Base:Exit>
        <Base:Climbable/>
      </Base:Detail>
      <Base:Detail id="ground" prime="false" def="true" abstract="false" hidden="false" luminosity="0" targetable_in_dark="false" plural="false">
        <Base:Preposition close="true" against="true" under="true" on="true" inside="false" near="true" over="false" behind="false" before="false" beside="false"/>
        <Base:Names>
          <Base:SNames>
            <Base:SName sname="floor"/>
            <Base:SName sname="ground"/>
            <Base:SName sname="paving"/>
            <Base:SName sname="pavement"/>
            <Base:SName sname="slab"/>
          </Base:SNames>
          <Base:PNames>
            <Base:PName pname="floors"/>
            <Base:PName pname="grounds"/>
            <Base:PName pname="pavements"/>
            <Base:PName pname="pavings"/>
            <Base:PName pname="slabs"/>
          </Base:PNames>
        </Base:Names>
        <Base:Adjectives>
          <Base:Adjective adjective="black"/>
          <Base:Adjective adjective="marble"/>
          <Base:Adjective adjective="stone"/>
          <Base:Adjective adjective="white"/>
        </Base:Adjectives>
        <Base:Descriptions>
          <Base:Description type="brief">
             the marble paving
          </Base:Description>
          <Base:Description type="look">
             The balcony is paved with square black and white marble slabs.
          </Base:Description>
        </Base:Descriptions>
        <Base:Exit door="false" closed="false" locked="false" never_obvious="false" obvious_when_open="false" hidden_when_closed="false" separate="false" self-locking="false" deadbolt="false"/>
        <Base:Climbable/>
      </Base:Detail>
      <Base:Detail id="railing" prime="false" def="true" abstract="false" hidden="false" luminosity="0" targetable_in_dark="false" plural="false">
        <Base:Preposition close="true" against="true" under="true" on="true" inside="true" near="true" over="true" behind="true" before="true" beside="true"/>
        <Base:Names>
          <Base:SNames>
            <Base:SName sname="rail"/>
            <Base:SName sname="railing"/>
          </Base:SNames>
          <Base:PNames>
            <Base:PName pname="railings"/>
            <Base:PName pname="rails"/>
          </Base:PNames>
        </Base:Names>
        <Base:Adjectives>
          <Base:Adjective adjective="balcony"/>
          <Base:Adjective adjective="marble"/>
          <Base:Adjective adjective="south"/>
          <Base:Adjective adjective="southern"/>
          <Base:Adjective adjective="stone"/>
        </Base:Adjectives>
        <Base:Descriptions>
          <Base:Description type="brief">
             the marble railing
          </Base:Description>
          <Base:Description type="look">
             A marble railing protects the open edge of the balcony; below and beyond the railing are the front lawns and the drive.
          </Base:Description>
        </Base:Descriptions>
        <Base:Exit door="false" closed="false" locked="false" never_obvious="false" obvious_when_open="false" hidden_when_closed="false" separate="false" self-locking="false" deadbolt="false"/>
        <Base:Climbable/>
      </Base:Detail>
      <Base:Detail id="view lawn south" prime="false" def="true" abstract="false" hidden="false" luminosity="0" targetable_in_dark="false" plural="false">
        <Base:Preposition close="false" against="false" under="false" on="false" inside="false" near="false" over="false" behind="false" before="false" beside="false"/>
        <Base:Names>
          <Base:SNames>
            <Base:SName sname="lawn"/>
            <Base:SName sname="step"/>
            <Base:SName sname="stair"/>
            <Base:SName sname="drive"/>
            <Base:SName sname="yard"/>
            <Base:SName sname="view"/>
            <Base:SName sname="outside"/>
          </Base:SNames>
          <Base:PNames>
            <Base:PName pname="drives"/>
            <Base:PName pname="lawns"/>
            <Base:PName pname="outsides"/>
            <Base:PName pname="stairs"/>
            <Base:PName pname="steps"/>
            <Base:PName pname="views"/>
            <Base:PName pname="yards"/>
          </Base:PNames>
        </Base:Names>
        <Base:Adjectives>
          <Base:Adjective adjective="dark"/>
          <Base:Adjective adjective="dim"/>
          <Base:Adjective adjective="front"/>
          <Base:Adjective adjective="south"/>
          <Base:Adjective adjective="southern"/>
          <Base:Adjective adjective="yard"/>
        </Base:Adjectives>
        <Base:Descriptions>
          <Base:Description type="brief">
             the view of the lawn and drive
          </Base:Description>
          <Base:Description type="examine">
             From this balcony, you can see: <br/><br/><describe-view type="look" view="OBJ(Mansion:rooms:Drive)"/>
          </Base:Description>
          <Base:Description type="look">
             From this balcony, you can see: <br/><br/><describe-view type="glance" view="OBJ(Mansion:rooms:Drive)"/>
          </Base:Description>
        </Base:Descriptions>
        <Base:Exit door="false" closed="false" locked="false" never_obvious="false" obvious_when_open="false" hidden_when_closed="false" separate="false" self-locking="false" deadbolt="false"/>
        <Base:Climbable/>
      </Base:Detail>
      <Base:Detail id="wall north" prime="false" def="true" abstract="false" hidden="false" luminosity="0" targetable_in_dark="false" plural="false">
        <Base:Preposition close="true" against="true" under="false" on="false" inside="false" near="true" over="false" behind="false" before="true" beside="false"/>
        <Base:Names>
          <Base:SNames>
            <Base:SName sname="wall"/>
            <Base:SName sname="side"/>
          </Base:SNames>
          <Base:PNames>
            <Base:PName pname="sides"/>
            <Base:PName pname="walls"/>
          </Base:PNames>
        </Base:Names>
        <Base:Adjectives>
          <Base:Adjective adjective="front"/>
          <Base:Adjective adjective="gray"/>
          <Base:Adjective adjective="masonry"/>
          <Base:Adjective adjective="north"/>
          <Base:Adjective adjective="northern"/>
          <Base:Adjective adjective="stone"/>
        </Base:Adjectives>
        <Base:Descriptions>
          <Base:Description type="brief">
             the front wall of the mansion
          </Base:Description>
          <Base:Description type="look">
             This balcony projects from the front wall of the mansion.
          </Base:Description>
        </Base:Descriptions>
        <Base:Exit door="false" closed="false" locked="false" never_obvious="false" obvious_when_open="false" hidden_when_closed="false" separate="false" self-locking="false" deadbolt="false"/>
        <Base:Climbable/>
      </Base:Detail>
    </Base:Details>
    <Base:Clothing>
      <Base:SingleWear value="false"/>
    </Base:Clothing>
    <Base:Crafting see_level="0" do_level="0" time="0" attention="false" held="false">
      <Base:Ingredients/>
      <Base:Tools/>
      <Base:CraftVerbs/>
    </Base:Crafting>
    <Base:InitialContents/>
    <Base:InitialProperties/>
    <Core:Properties>
      <Core:Property property="revisions">
         (\{ 1172508143, "-", "SYNC" \})
      </Core:Property>
      <Core:Property property="skill:fatigue">100.0</Core:Property>
      <Core:Property property="volition">0</Core:Property>
    </Core:Properties>
    <Notes:Notes>
      <Notes:Category cat="Comment" catstate="Open">
        <Notes:Note ix="967605331" state="Comment" user="michaelb">
           The balcony looking over the front.
        </Notes:Note>
      </Notes:Category>
    </Notes:Notes>
  </Base:Thing>
</object>
