<object clone="/usr/SkotOS/obj/verb" owner="Socials">
  <Socials:Verb imp="haul" second="haul" third="hauls" evoke="optional" audible="false" private="false" secret="false" obscured="false" target-abstracts="false" disabled="false" ooc="false" raw_verb="false">
    <Ur:UrObject/>
    <Socials:SocialObjects>
      <Socials:SocialObject role="dob" direct="true" single="false" raw="false" requirement="optional" distance="armslength">
        <Socials:SocObPreps/>
        <Socials:SocObFilters/>
      </Socials:SocialObject>
      <Socials:SocialObject role="iob" direct="false" single="false" raw="false" requirement="optional" distance="armslength">
        <Socials:SocObPreps>
          <Socials:SocObPrep prep="to"/>
          <Socials:SocObPrep prep="into"/>
          <Socials:SocObPrep prep="over"/>
          <Socials:SocObPrep prep="around"/>
          <Socials:SocObPrep prep="behind"/>
          <Socials:SocObPrep prep="from"/>
          <Socials:SocObPrep prep="onto"/>
          <Socials:SocObPrep prep="toward"/>
          <Socials:SocObPrep prep="towards"/>
          <Socials:SocObPrep prep="with"/>
          <Socials:SocObPrep prep="by"/>
        </Socials:SocObPreps>
        <Socials:SocObFilters/>
      </Socials:SocialObject>
    </Socials:SocialObjects>
    <Socials:VerbActions/>
    <Core:Properties>
      <Core:Property property="revisions">
         (\{ 1068290282, "sorcha", "X", 1070233217, "sorcha", "X", 1079793328, "tangerine", "X", 1080305552, "tangerine", "E", 1080305604, "tangerine", "E", 1080305780, "tangerine", "E", 1080305803, "tangerine", "E", 1080305900, "tangerine", "E", 1080305931, "tangerine", "E", 1080305949, "tangerine", "E", 1080305980, "tangerine", "E", 1080306000, "tangerine", "E", 1080306080, "tangerine", "E", 1080306092, "tangerine", "E", 1080306295, "tangerine", "E", 1080306310, "tangerine", "E", 1082562357, "tangerine", "E", 1184317601, "sinvyrae", "E", 1184317618, "sinvyrae", "E", 1184396928, "???", "R", 1284266975, "slurpeeslurp", "E", 1284266985, "slurpeeslurp", "E", 1284267013, "slurpeeslurp", "E", 1284267013, "slurpeeslurp", "E", 1284267020, "slurpeeslurp", "E", 1284267031, "slurpeeslurp", "E", 1284267093, "slurpeeslurp", "E", 1284267112, "slurpeeslurp", "E", 1284267155, "slurpeeslurp", "E", 1284267164, "slurpeeslurp", "E", 1284267176, "slurpeeslurp", "E", 1284267180, "slurpeeslurp", "E", 1284267185, "slurpeeslurp", "E", 1284267200, "slurpeeslurp", "E", 1284267204, "slurpeeslurp", "E", 1284267208, "slurpeeslurp", "E", 1284267216, "slurpeeslurp", "E", 1284267274, "slurpeeslurp", "E", 1284267347, "slurpeeslurp", "E", 1284267352, "slurpeeslurp", "E", 1284267365, "slurpeeslurp", "E", 1284267522, "slurpeeslurp", "E", 1284275633, "???", "R" \})
      </Core:Property>
      <Core:Property property="sys:sync:clearing">0</Core:Property>
      <Core:Property property="sys:sync:imported">
         1284275633
      </Core:Property>
      <Core:Property property="sys:sync:proposing-revision">
         1284267522
      </Core:Property>
    </Core:Properties>
    <Notes:Notes/>
  </Socials:Verb>
</object>
