<object clone="/usr/SkotOS/obj/verb" owner="Socials">
  <Socials:Verb imp="devour" second="devour" third="devours" evoke="optional" audible="false" private="false" secret="false" obscured="false" target-abstracts="false" disabled="false" ooc="false" raw_verb="false">
    <Ur:UrObject/>
    <Socials:SocialObjects>
      <Socials:SocialObject role="dob" direct="true" single="false" raw="false" requirement="optional" distance="close">
        <Socials:SocObPreps/>
        <Socials:SocObFilters/>
      </Socials:SocialObject>
      <Socials:SocialObject role="iob" direct="false" single="false" raw="false" requirement="optional" distance="close">
        <Socials:SocObPreps>
          <Socials:SocObPrep prep="into"/>
          <Socials:SocObPrep prep="with"/>
        </Socials:SocObPreps>
        <Socials:SocObFilters/>
      </Socials:SocialObject>
    </Socials:SocialObjects>
    <Socials:VerbActions/>
    <Core:Properties>
      <Core:Property property="nip:all:flags">1975</Core:Property>
      <Core:Property property="nip:all:strength">4</Core:Property>
      <Core:Property property="nip:author">
         "lunamoon"
      </Core:Property>
      <Core:Property property="revisions">
         (\{ 1059768173, "sorcha", "X", 1059768319, "sorcha", "E", 1059768330, "sorcha", "X", 1059768377, "sorcha", "E", 1059768485, "sorcha", "E", 1111015352, "arkenstone", "X", 1159255139, "zwoc", "NIP", 1208784216, "sinvyrae", "E", 1208784224, "sinvyrae", "E", 1208784231, "sinvyrae", "E", 1208784249, "sinvyrae", "E", 1208848416, "???", "R" \})
      </Core:Property>
      <Core:Property property="sys:sync:clearing">0</Core:Property>
      <Core:Property property="sys:sync:imported">
         1208848416
      </Core:Property>
      <Core:Property property="sys:sync:proposing-revision">
         1208784249
      </Core:Property>
    </Core:Properties>
    <Notes:Notes/>
  </Socials:Verb>
</object>
