<object clone="/usr/SkotOS/obj/verb" owner="SkotOS">
  <Socials:Verb imp="!suspend" evoke="forbidden" audible="false" private="false" secret="false" obscured="false" target-abstracts="false" disabled="false" ooc="false" raw_verb="true">
    <Ur:UrObject urobject="OBJ(Neoct:Staff:Verbs:+suspend)"/>
    <Socials:SocialObjects/>
    <Socials:VerbActions/>
    <Core:Properties>
      <Core:Property property="revisions">
         (\{ 1144052091, "-", "SYNC", 1641669036, "bobo", "E", 1641669045, "bobo", "E" \})
      </Core:Property>
    </Core:Properties>
    <Notes:Notes/>
  </Socials:Verb>
</object>
