<object clone="/obj/properties" owner="zwoc">
  <Core:PropertyContainer>
    <Ur:UrObject/>
    <Core:PCProperties>
      <Core:Property property="ncs:connections">
         ([ \<Mansion:examples:snowball\>:"ncs:handler", \<Mansion:lib:jonkichi:butler\>:"ncs:handler", \<Mansion:lib:jonkichi:hat-girl\>:"ncs:handler" ])
      </Core:Property>
      <Core:Property property="ncs:pkg_link">
         ([ "joi":\<Lib:NIP:pkg:base\>, "join":\<Lib:NIP:pkg:base\>, "live":\<Lib:NIP:pkg:base\>, "popup":\<Lib:NIP:pkg:base\>, "purge":\<Lib:NIP:pkg:base\>, "scrolls-date":\<Lib:NIP:pkg:delivery\>, "scrolls-from":\<Lib:NIP:pkg:delivery\>, "scrolls-to":\<Lib:NIP:pkg:delivery\>, "status":\<Lib:NIP:pkg:base\>, "update":\<Lib:NIP:pkg:base\>, "where":\<Lib:NIP:pkg:base\> ])
      </Core:Property>
      <Core:Property property="ncs:signatures">
         ([ \<Mansion:examples:snowball\>:"UrKitty-2", \<Mansion:lib:jonkichi:butler\>:"butler-2", \<Mansion:lib:jonkichi:hat-girl\>:"hat-girl-0" ])
      </Core:Property>
      <Core:Property property="revisions">
         (\{ 1063849724, "zwoc", "X" \})
      </Core:Property>
    </Core:PCProperties>
    <Notes:Notes/>
  </Core:PropertyContainer>
</object>
