<object clone="/obj/properties" owner="TextIF">
  <Core:PropertyContainer>
    <Ur:UrObject/>
    <Core:PCProperties>
      <Core:Property property="revisions">
         (\{ 1135371478, "-", "SYNC" \})
      </Core:Property>
      <Core:Property property="tool:broadcast">
         \<Lib:misc:EmitAppTools\>
      </Core:Property>
      <Core:Property property="tool:emitperson">
         \<Lib:misc:EmitAppTools\>
      </Core:Property>
      <Core:Property property="tool:emitroom">
         \<Lib:misc:EmitAppTools\>
      </Core:Property>
      <Core:Property property="tool:emitrooms">
         \<Lib:misc:EmitAppTools\>
      </Core:Property>
      <Core:Property property="tool:emitsourced">
         \<Lib:misc:EmitAppTools\>
      </Core:Property>
      <Core:Property property="tool:list">
         (\{ "pause", "emitperson", "emitroom", "emitrooms", "broadcast", "emitsourced", "randomemit", "loop" \})
      </Core:Property>
      <Core:Property property="tool:loop">
         \<Lib:misc:EmitAppTools\>
      </Core:Property>
      <Core:Property property="tool:pause">
         \<Lib:misc:EmitAppTools\>
      </Core:Property>
      <Core:Property property="tool:randomemit">
         \<Lib:misc:EmitAppTools\>
      </Core:Property>
    </Core:PCProperties>
    <Notes:Notes>
      <Notes:Category cat="QA" catstate="Open">
        <Notes:Note ix="1077300347" state="Comment" user="zwoc">
           This is a data-object used by the +EmitApp tool to get a list of available, external tools.
A tool is listed in the "tool:list" array; each tool has a "tool:NAME" property, pointing to the object in which the tool's "html:tool_NAME" property (hopefully) exists. If no "tool:NAME" property exists, the script is expected to exist in this data object.
        </Notes:Note>
      </Notes:Category>
    </Notes:Notes>
  </Core:PropertyContainer>
</object>
