<object clone="/obj/properties" owner="TextIF">
  <Core:PropertyContainer>
    <Ur:UrObject/>
    <Core:PCProperties>
      <Core:Property property="merry:inherit:lib:touch_trash">
         \<Lib:trash\>
      </Core:Property>
      <Core:Property property="trash:data">
         ([ 1:([  ]), 26:([  ]) ])
      </Core:Property>
      <Core:Property property="trash:land-name">
         "nowland"
      </Core:Property>
    </Core:PCProperties>
    <Notes:Notes/>
  </Core:PropertyContainer>
</object>
